nonebot_plugin_htmlkit/__init__.py
nonebot_plugin_htmlkit/config.py
nonebot_plugin_htmlkit/core.abi3.so
nonebot_plugin_htmlkit/core.pyi
nonebot_plugin_htmlkit/templates/github-markdown-light.css
nonebot_plugin_htmlkit/templates/markdown.html
nonebot_plugin_htmlkit/templates/pygments-default.css
nonebot_plugin_htmlkit/templates/text.css
nonebot_plugin_htmlkit/templates/text.html
nonebot_plugin_htmlkit-0.1.0rc5.dist-info/METADATA
nonebot_plugin_htmlkit-0.1.0rc5.dist-info/WHEEL
nonebot_plugin_htmlkit-0.1.0rc5.dist-info/top_level.txt
nonebot_plugin_htmlkit-0.1.0rc5.dist-info/RECORD
nonebot_plugin_htmlkit-0.1.0rc5.dist-info/licenses/LICENSE
