Metadata-Version: 2.4
Name: nonebot-plugin-htmlkit
Version: 0.1.0rc5
Summary: Lightweight HTML rendering plugin for NoneBot
Maintainer-email: Nyuan Zhang <blueglassblock@outlook.com>
License-Expression: MIT AND LGPL-3.0-or-later
Project-URL: Homepage, https://github.com/nonebot/plugin-htmlkit
Project-URL: Repository, https://github.com/nonebot/plugin-htmlkit.git
Project-URL: Issues, https://github.com/nonebot/plugin-htmlkit/issues
Keywords: nonebot,nonebot2,htmlkit,litehtml,html
Classifier: Development Status :: 4 - Beta
Classifier: Intended Audience :: Developers
Classifier: Programming Language :: Python :: Implementation :: CPython
Classifier: Topic :: Software Development :: Libraries :: Python Modules
Classifier: Framework :: AsyncIO
Classifier: Programming Language :: Python :: 3.10
Classifier: Programming Language :: Python :: 3.11
Classifier: Programming Language :: Python :: 3.12
Classifier: Programming Language :: Python :: 3.13
Classifier: Programming Language :: Python :: 3.14
Requires-Python: >=3.10
License-File: LICENSE
Requires-Dist: aiofiles>=0.8.0
Requires-Dist: jinja2>=3.0.3
Requires-Dist: markdown>=3.3.6
Requires-Dist: nonebot2~=2.3
Requires-Dist: pygments>=2.10.0
Requires-Dist: pymdown-extensions>=9.1
Dynamic: license-file
